sneakers/__init__.py
sneakers/globalimports.py
sneakers/layout.py
sneakers/scrollbar.py
sneakers/threadtools.py
sneakers/tkimports.py
sneakers/widgets.py
sneakers/window.py
sneakers/ttk/__init__.py
sneakers/ttk/globalimports.py
sneakers/ttk/layout.py
sneakers/ttk/scrollbar.py
sneakers/ttk/threadtools.py
sneakers/ttk/ttkimports.py
sneakers/ttk/widgets.py
sneakers/ttk/window.py
sneakers/ttk/utils/__init__.py
sneakers/ttk/utils/window_tools.py
sneakers-0.0.1.dist-info/DESCRIPTION.rst
sneakers-0.0.1.dist-info/METADATA
sneakers-0.0.1.dist-info/RECORD
sneakers-0.0.1.dist-info/WHEEL
sneakers-0.0.1.dist-info/metadata.json
sneakers-0.0.1.dist-info/top_level.txt
