Metadata-Version: 2.0
Name: sneakers
Version: 0.0.1
Summary: Ruby shoes flavored tkinter.
Home-page: https://github.com/draperjames/sneakers
Author: James Draper
Author-email: james.draper@duke.edu
License: MIT
Keywords: gui,shoes,tkinter
Platform: POSIX
Platform: Windows
Classifier: Development Status :: 5 - Production/Stable
Classifier: License :: OSI Approved :: MIT License
Classifier: Operating System :: Microsoft :: Windows
Classifier: Operating System :: POSIX
Classifier: Programming Language :: Python :: 2.6
Classifier: Programming Language :: Python :: 2.7
Classifier: Programming Language :: Python :: 3
Classifier: Programming Language :: Python :: 3.3
Classifier: Programming Language :: Python :: 3.4
Classifier: Programming Language :: Python :: 3.5
Classifier: Programming Language :: Python :: 3.6
Classifier: Programming Language :: Python :: 3.7
Classifier: Topic :: Software Development :: Build Tools
Classifier: Topic :: System :: Systems Administration
Provides: sneakers
